ChaosIntelligence/__init__.py
ChaosIntelligence/modules/Core.py
ChaosIntelligence/modules/DeterministicFunctions.py
ChaosIntelligence/modules/OverlayLayer.py
ChaosIntelligence/modules/__init__.py
Chaos_Intelligence-0.0.2.dev202202.dist-info/LICENSE
Chaos_Intelligence-0.0.2.dev202202.dist-info/METADATA
Chaos_Intelligence-0.0.2.dev202202.dist-info/WHEEL
Chaos_Intelligence-0.0.2.dev202202.dist-info/top_level.txt
Chaos_Intelligence-0.0.2.dev202202.dist-info/RECORD
