Metadata-Version: 2.1
Name: Chaos-Intelligence
Version: 0.0.2.dev202202
Summary: Responsive Neural Network Layers
Home-page: https://github.com/SilverousBlack/Chaos-Intelligence
Author: SilverousBlack
Author-email: mail.silverousblack@gmail.com
License: UNKNOWN
Project-URL: Bug Tracker, https://github.com/SilverousBlack/Chaos-Intelligence/issues
Platform: UNKNOWN
Classifier: Programming Language :: Python :: 3
Classifier: License :: OSI Approved :: MIT License
Classifier: Operating System :: OS Independent
Requires-Python: >=3.6
License-File: LICENSE
